mdns_beacon/__init__.py
mdns_beacon/base.py
mdns_beacon/beacon.py
mdns_beacon/cli/__init__.py
mdns_beacon/cli/layouts.py
mdns_beacon/cli/main.py
mdns_beacon/cli/types.py
mdns_beacon/listener.py
mdns_beacon-1.0.0.dist-info/LICENSE.rst
mdns_beacon-1.0.0.dist-info/METADATA
mdns_beacon-1.0.0.dist-info/WHEEL
mdns_beacon-1.0.0.dist-info/entry_points.txt
mdns_beacon-1.0.0.dist-info/RECORD
