Metadata-Version: 2.1
Name: mdns-beacon
Version: 1.0.0
Summary: Multicast DNS (mDNS) Beacon to announce multiple CNAME aliases across your local network.
Home-page: https://github.com/fedejaure/mdns-beacon
Keywords: mdns-beacon,mdns,beacon,avahi,zeroconf,bonjour
Author: Federico Jaureguialzo
Author-email: fedejaure@gmail.com
Requires-Python: >=3.10,<3.13
Classifier: Development Status :: 2 - Pre-Alpha
Classifier: Intended Audience :: Developers
Classifier: License :: OSI Approved :: MIT License
Classifier: Natural Language :: English
Classifier: Programming Language :: Python :: 3
Classifier: Programming Language :: Python :: 3.10
Classifier: Programming Language :: Python :: 3.11
Classifier: Programming Language :: Python :: 3.12
Requires-Dist: click (>=8.1.7,<9.0.0)
Requires-Dist: click-option-group (>=0.5.6,<0.6.0)
Requires-Dist: python-slugify (>=8.0.4,<9.0.0)
Requires-Dist: rich (>=13.8.0,<14.0.0)
Requires-Dist: typing-extensions (>=4.12.2,<5.0.0)
Requires-Dist: zeroconf (>=0.134.0,<0.135.0)
Project-URL: Bug Tracker, https://github.com/fedejaure/mdns-beacon/issues
Project-URL: Documentation, https://mdns-beacon.readthedocs.io
Project-URL: Repository, https://github.com/fedejaure/mdns-beacon
